personal_assistant/__init__.py
personal_assistant/commands.py
personal_assistant/main.py
personal_assistant/menus.py
personal_assistant/src/__init__.py
personal_assistant/src/messages.py
personal_assistant/src/personal_assistant.py
personal_assistant/src/utils.py
personal_assistant/src/contacts/__init__.py
personal_assistant/src/contacts/contacts.py
personal_assistant/src/contacts/fields.py
personal_assistant/src/contacts/record.py
personal_assistant/src/exceptions/__init__.py
personal_assistant/src/exceptions/exceptions.py
personal_assistant/src/notes/__init__.py
personal_assistant/src/notes/note.py
personal_assistant/src/notes/notes.py
personal_assistant_py_br-0.0.1.dist-info/LICENSE
personal_assistant_py_br-0.0.1.dist-info/METADATA
personal_assistant_py_br-0.0.1.dist-info/WHEEL
personal_assistant_py_br-0.0.1.dist-info/entry_points.txt
personal_assistant_py_br-0.0.1.dist-info/top_level.txt
personal_assistant_py_br-0.0.1.dist-info/RECORD
