Metadata-Version: 2.1
Name: personal_assistant_py_br
Version: 0.0.1
Summary: A personal assistant.
Home-page: https://github.com/nazarsmith/ppap7856-pythoneers-brigade-prjct
Author: Nazar Stakhovskyi
Author-email: nazarstahovsky@gmail.com
License: MIT
Classifier: Programming Language :: Python :: 3.7
Classifier: Programming Language :: Python :: 3.8
Classifier: Programming Language :: Python :: 3.9
Classifier: Programming Language :: Python :: 3.10
Classifier: Programming Language :: Python :: 3.11
Classifier: Programming Language :: Python :: 3.12
License-File: LICENSE
